PayGmailScraper/__init__.py
PayGmailScraper/gmail_setup.py
PayGmailScraper/parse_gmail_base.py
PayGmailScraper/pay_gmail_scraper.py
PayGmailScraper/payment_information.py
PayGmailScraper/payment/ana_pay.py
PayGmailScraper/payment/rakuten_pay.py
PyGmailScraper-1.1.3.dist-info/LICENSE.txt
PyGmailScraper-1.1.3.dist-info/METADATA
PyGmailScraper-1.1.3.dist-info/WHEEL
PyGmailScraper-1.1.3.dist-info/top_level.txt
PyGmailScraper-1.1.3.dist-info/RECORD
