Metadata-Version: 2.1
Name: PyGmailScraper
Version: 1.1.3
Summary: Retrieve payment information, including QR code payments and credit card, from Gmail.
Author-email: tra <tisk0711ngm@gmail.com>
Maintainer-email: tra <tisk0711ngm@gmail.com>
License: MIT License
Project-URL: Source, https://github.com/clcl777/PayGmailScraper
Classifier: Development Status :: 5 - Production/Stable
Classifier: Intended Audience :: Developers
Classifier: Programming Language :: Python :: 3
Classifier: Environment :: Web Environment
Classifier: License :: OSI Approved :: MIT License
Classifier: Operating System :: OS Independent
Classifier: Typing :: Typed
Classifier: Topic :: Software Development
Requires-Python: >=3.8
License-File: LICENSE.txt
Requires-Dist: google-api-python-client >=2.111.0
Requires-Dist: google-auth >=2.29.0
Requires-Dist: google-auth-oauthlib >=1.2.0
Requires-Dist: python-dateutil >=2.8.2
Provides-Extra: dev
Requires-Dist: build ; extra == 'dev'
Requires-Dist: twine ; extra == 'dev'
Requires-Dist: types-python-dateutil ; extra == 'dev'
